docxtpl_checker.py
docxtpl_checker-0.0.1.dist-info/licenses/LICENSE
docxtpl_checker-0.0.1.dist-info/METADATA
docxtpl_checker-0.0.1.dist-info/WHEEL
docxtpl_checker-0.0.1.dist-info/entry_points.txt
docxtpl_checker-0.0.1.dist-info/top_level.txt
docxtpl_checker-0.0.1.dist-info/RECORD
