Metadata-Version: 2.4
Name: docxtpl-checker
Version: 0.0.1
Summary: A comprehensive validation tool for python-docx-template (docxtpl) Word templates
Home-page: https://github.com/VicBioDev/docxtpl_checker
Author: Docxtpl Template Checker
Author-email: vic.wangyifan@gmail.com
Project-URL: Bug Reports, https://github.com/VicBioDev/docxtpl_checker/issues
Project-URL: Source, https://github.com/VicBioDev/docxtpl_checker
Project-URL: Documentation, https://github.com/VicBioDev/docxtpl_checker#readme
Keywords: docxtpl jinja2 template validation word document docx
Classifier: Development Status :: 5 - Production/Stable
Classifier: Intended Audience :: Developers
Classifier: License :: OSI Approved :: MIT License
Classifier: Operating System :: OS Independent
Classifier: Programming Language :: Python :: 3
Classifier: Programming Language :: Python :: 3.6
Classifier: Programming Language :: Python :: 3.7
Classifier: Programming Language :: Python :: 3.8
Classifier: Programming Language :: Python :: 3.9
Classifier: Programming Language :: Python :: 3.10
Classifier: Programming Language :: Python :: 3.11
Classifier: Topic :: Software Development :: Quality Assurance
Classifier: Topic :: Text Processing :: Markup
Classifier: Topic :: Office/Business :: Office Suites
Requires-Python: >=3.6
License-File: LICENSE
Requires-Dist: jinja2>=2.10
Dynamic: author
Dynamic: author-email
Dynamic: classifier
Dynamic: description
Dynamic: description-content-type
Dynamic: home-page
Dynamic: keywords
Dynamic: license-file
Dynamic: project-url
Dynamic: requires-dist
Dynamic: requires-python
Dynamic: summary
